gather_client_ws/__init__.py
gather_client_ws/actions.py
gather_client_ws/client.py
gather_client_ws/events_pb2.py
gather_client_ws/helpers.py
gather_client_ws-0.0.4.dist-info/LICENSE
gather_client_ws-0.0.4.dist-info/METADATA
gather_client_ws-0.0.4.dist-info/WHEEL
gather_client_ws-0.0.4.dist-info/top_level.txt
gather_client_ws-0.0.4.dist-info/RECORD
