Metadata-Version: 2.1
Name: gather-client-ws
Version: 0.0.4
Summary: Gather WebSocket service client
Home-page: https://github.com/pyanderson/gather-client-ws
Author: Anderson de Sousa Lima
Author-email: hello@pyanderson.dev
License: MIT
Keywords: gather,gather-town,websocket
Classifier: Development Status :: 5 - Production/Stable
Classifier: Intended Audience :: Developers
Classifier: License :: OSI Approved :: MIT License
Classifier: Natural Language :: English
Classifier: Programming Language :: Python :: 3
Classifier: Programming Language :: Python :: 3.4
Classifier: Programming Language :: Python :: 3.5
Classifier: Programming Language :: Python :: 3.6
Classifier: Programming Language :: Python :: 3.7
Classifier: Programming Language :: Python :: 3.8
Classifier: Programming Language :: Python :: 3.9
License-File: LICENSE
Requires-Dist: tapioca-gather (<1)
Requires-Dist: protobuf (==4.22.1)
Requires-Dist: websockets (==10.4)
